retricon/__init__.py
retricon/retricon.py
retricon-1.3.3.dist-info/licenses/LICENSE.txt
retricon-1.3.3.dist-info/METADATA
retricon-1.3.3.dist-info/WHEEL
retricon-1.3.3.dist-info/top_level.txt
retricon-1.3.3.dist-info/RECORD
