Metadata-Version: 2.4
Name: retricon
Version: 1.3.3
Summary: A library to create icons similar to Github avatars
Author-email: Raphael Stefanini <raphael@rphlo.com>
License-Expression: MIT
Project-URL: Homepage, https://github.com/rphlo/py-retricon
Keywords: image,avatar,icon,identicon
Classifier: Programming Language :: Python
Requires-Python: >=3
License-File: LICENSE.txt
Requires-Dist: pillow
Dynamic: license-file
